Workbook

Sheet README
A2: Section | B2: Details
A3: Purpose | B3: This workbook supports a BankUnited master class on AI-assisted data analytics in Excel.
A4: Important Data Notice | B4: All data is synthetic training data created for demonstration only. It does not contain BankUnited customer, employee, account, or proprietary data.
A5: Demo 1 | B5: Build an AI-assisted financial model for an analytics enablement initiative using assumptions, scenarios, and branch context.
A6: Demo 2 | B6: Run and explain a Monte Carlo analysis to show the range of possible business outcomes rather than pretending one forecast is certain.
A7: How to Use with Copilot in Excel | B7: Save this workbook to OneDrive or SharePoint with AutoSave on, open it in Excel, and use Copilot from the Home tab against the provided tables.
A8: Responsible Use | B8: Copilot output must be reviewed, verified, and interpreted by people, especially in banking contexts involving risk, compliance, customers, or capital decisions.
A9: Financial_Model_Live_Build | B9: Blank live-build model table for Demo 1. Use Copilot to create formulas and summaries from assumptions.
A10: Monte_Carlo_Live_Build | B10: Blank live-build simulation table for Demo 2. Use Copilot to create/randomize trials and summarize risk.
A11: Agent_Workflow_Blueprint | B11: Template for turning the spreadsheet process into a repeatable, shareable human-supervised agent workflow.

Sheet Branch_Monthly_Data
A2: Month | B2: Branch | C2: Market | D2: Primary Segment | E2: Customer Accounts | F2: New Accounts | G2: Average Deposits | H2: Average Loans | I2: Loan Yield | J2: Cost of Funds | K2: Fee Income | L2: Operating Expense | M2: Credit Loss Provision | N2: Digital Adoption Rate | O2: NIM Dollars | P2: Monthly Contribution Profit
A3: 46023 | B3: Miami Lakes | C3: Miami-Dade | D3: Retail Banking | E3: 10329 | F3: 176 | G3: 3.4510011e+08 | H3: 4.215569e+08 | I3: 0.06351 | J3: 0.03046 | K3: 220720.44 | L3: 628519.86 | M3: 301396.8 | N3: 0.583 | O3: 1355109.8 | P3: 645913.57
A4: 46054 | B4: Miami Lakes | C4: Miami-Dade | D4: Retail Banking | E4: 10273 | F4: 178 | G4: 3.5800437e+08 | H4: 4.3648185e+08 | I4: 0.06881 | J4: 0.03149 | K4: 197123.81 | L4: 694791.78 | M4: 725531.83 | N4: 0.5743 | O4: 1563312 | P4: 340112.22
A5: 46082 | B5: Miami Lakes | C5: Miami-Dade | D5: Retail Banking | E5: 10313 | F5: 163 | G5: 3.4493333e+08 | H5: 4.1652027e+08 | I5: 0.06924 | J5: 0.0285 | K5: 253897.37 | L5: 743945.16 | M5: 454715.46 | N5: 0.5718 | O5: 1584047.4 | P5: 639284.19
A6: 46113 | B6: Miami Lakes | C6: Miami-Dade | D6: Retail Banking | E6: 10434 | F6: 144 | G6: 3.5267395e+08 | H6: 4.2054146e+08 | I6: 0.06396 | J6: 0.03526 | K6: 235965.26 | L6: 734445.08 | M6: 449677.77 | N6: 0.6219 | O6: 1205099 | P6: 256941.4
A7: 46143 | B7: Miami Lakes | C7: Miami-Dade | D7: Retail Banking | E7: 10346 | F7: 145 | G7: 3.5801949e+08 | H7: 4.2836698e+08 | I7: 0.0655 | J7: 0.03181 | K7: 177877.61 | L7: 685305.94 | M7: 334660.02 | N7: 0.6103 | O7: 1389261.2 | P7: 547172.82
A8: 46174 | B8: Miami Lakes | C8: Miami-Dade | D8: Retail Banking | E8: 10480 | F8: 181 | G8: 3.4864771e+08 | H8: 4.4523386e+08 | I8: 0.06269 | J8: 0.03318 | K8: 235184.82 | L8: 613855.82 | M8: 424726.4 | N8: 0.6135 | O8: 1362040.4 | P8: 558642.97
A9: 46204 | B9: Miami Lakes | C9: Miami-Dade | D9: Retail Banking | E9: 10483 | F9: 159 | G9: 3.5889236e+08 | H9: 4.2498418e+08 | I9: 0.06719 | J9: 0.0292 | K9: 188862.8 | L9: 663634.94 | M9: 400954.73 | N9: 0.6178 | O9: 1506129.1 | P9: 630402.25
A10: 46235 | B10: Miami Lakes | C10: Miami-Dade | D10: Retail Banking | E10: 10583 | F10: 174 | G10: 3.4989238e+08 | H10: 4.4443895e+08 | I10: 0.05811 | J10: 0.03354 | K10: 193953.08 | L10: 641332.56 | M10: 383828.83 | N10: 0.6342 | O10: 1173972.4 | P10: 342764.05
A11: 46266 | B11: Miami Lakes | C11: Miami-Dade | D11: Retail Banking | E11: 10703 | F11: 225 | G11: 3.5324156e+08 | H11: 4.4176815e+08 | I11: 0.06165 | J11: 0.03001 | K11: 171718.07 | L11: 834285.84 | M11: 233583.8 | N11: 0.6305 | O11: 1386252.9 | P11: 490101.34
A12: 46296 | B12: Miami Lakes | C12: Miami-Dade | D12: Retail Banking | E12: 10633 | F12: 195 | G12: 3.5869449e+08 | H12: 4.4339738e+08 | I12: 0.05621 | J12: 0.02603 | K12: 171534.74 | L12: 755548.27 | M12: 449562.16 | N12: 0.6556 | O12: 1298920.9 | P12: 265345.16
A13: 46327 | B13: Miami Lakes | C13: Miami-Dade | D13: Retail Banking | E13: 10615 | F13: 160 | G13: 3.5017491e+08 | H13: 4.5065757e+08 | I13: 0.06536 | J13: 0.02677 | K13: 201350.71 | L13: 623696.24 | M13: 771615.59 | N13: 0.704 | O13: 1673258.5 | P13: 479297.34
A14: 46357 | B14: Miami Lakes | C14: Miami-Dade | D14: Retail Banking | E14: 10778 | F14: 143 | G14: 3.6202574e+08 | H14: 4.4454042e+08 | I14: 0.06181 | J14: 0.02545 | K14: 258250.36 | L14: 612350.05 | M14: 450406.46 | N14: 0.6691 | O14: 1522196.2 | P14: 717690.04
... A98: 46357 | B98: Naples | C98: Collier | D98: Private Banking | E98: 12739 | F98: 135 | G98: 3.2814313e+08 | H98: 3.41494e+08 | I98: 0.06111 | J98: 0.03239 | K98: 193835.43 | L98: 706871.86 | M98: 235888.93 | N98: 0.7101 | O98: 853519.99 | P98: 104594.63

Sheet Model_Assumptions
A2: Input | B2: Value | C2: Plain English Meaning
A3: Initial analytics enablement investment | B3: 350000 | C3: One-time training, governance, templates, data preparation, and adoption investment.
A4: Monthly incremental analyst capacity value | B4: 85000 | C4: Estimated monthly value from time saved by relationship managers, analysts, and operations staff.
A5: Base monthly operating benefit | B5: 125000 | C5: Base month one benefit from faster analysis, better exception detection, and improved decision support.
A6: Annual benefit growth rate | B6: 0.12 | C6: Expected compounding improvement as more teams reuse the model and prompt patterns.
A7: Implementation operating cost per month | B7: 28000 | C7: Ongoing cost for stewardship, refresh cycles, coaching, controls, and model maintenance.
A8: Discount rate | B8: 0.105 | C8: Bank hurdle rate used for discounting future benefits.
A9: Planning horizon in months | B9: 36 | C9: Three-year planning view.
A10: Base case probability of success | B10: 0.62 | C10: Probability that the base case adoption plan reaches expected utilization.
A11: Upside case probability of success | B11: 0.78 | C11: Probability assumption for accelerated adoption and strong executive sponsorship.
A12: Downside case probability of success | B12: 0.42 | C12: Probability assumption for stalled adoption or low workflow integration.

Sheet Scenario_Assumptions
A2: Scenario | B2: Adoption Rate | C2: Benefit Multiplier | D2: Cost Multiplier | E2: Risk Adjustment | F2: Narrative
A3: Downside | B3: 0.35 | C3: 0.55 | D3: 1.15 | E3: 0.8 | F3: Low adoption, limited manager follow-through, and manual processes remain dominant.
A4: Base | B4: 0.62 | C4: 1 | D4: 1 | E4: 0.92 | F4: Steady rollout with coached use cases, repeatable templates, and manager reinforcement.
A5: Upside | B5: 0.82 | C5: 1.45 | D5: 0.92 | E5: 0.97 | F5: High adoption with reusable models, strong governance, and visible leadership sponsorship.

Sheet Financial_Model_Live_Build
A2: LIVE BUILD SHEET: Financial Model
A3: Purpose: Start here during the demo. Copilot should help create the formulas, summaries, charts, and verification checks. The finished Financial_Model sheet remains only as an answer key/reset option.
A4: Presenter note: Ask Copilot to build the model from Model_Assumptions and Scenario_Assumptions; do not begin by opening the finished Financial_Model sheet.
A6: Month Number | B6: Scenario | C6: Adoption Rate | D6: Gross Benefit | E6: Risk-Adjusted Benefit | F6: Operating Cost | G6: Net Monthly Benefit | H6: Cumulative Net Benefit | I6: Discount Factor | J6: Present Value | K6: Formula Verification Note
A7: 1 | B7: Downside
A8: 2 | B8: Downside
A9: 3 | B9: Downside
A10: 4 | B10: Downside
A11: 5 | B11: Downside
A12: 6 | B12: Downside
A13: 7 | B13: Downside
A14: 8 | B14: Downside
A15: 9 | B15: Downside
A16: 10 | B16: Downside
A17: 11 | B17: Downside
A18: 12 | B18: Downside
... A114: 36 | B114: Upside

Sheet Financial_Model
A2: Month Number | B2: Scenario | C2: Adoption Rate | D2: Gross Benefit | E2: Risk-Adjusted Benefit | F2: Operating Cost | G2: Net Monthly Benefit | H2: Cumulative Net Benefit | I2: Discount Factor | J2: Present Value
A3: 1 | B3: Downside | C3: 0.35 | D3: 40425 | E3: 32340 | F3: 32200 | G3: 140 | H3: =G3-Model_Assumptions!$B$3 -> -349860 | I3: =1/(1+Model_Assumptions!$B$8/12)^A3 -> 0.9913259 | J3: =G3*I3 -> 138.78563
A4: 1 | B4: Base | C4: 0.62 | D4: 130200 | E4: 119784 | F4: 28000 | G4: 91784 | H4: =IF(B4=B3,H3+G4,G4-Model_Assumptions!$B$3) -> -258216 | I4: =1/(1+Model_Assumptions!$B$8/12)^A4 -> 0.9913259 | J4: =G4*I4 -> 90987.856
A5: 1 | B5: Upside | C5: 0.82 | D5: 249690 | E5: 242199.3 | F5: 25760 | G5: 216439.3 | H5: =IF(B5=B4,H4+G5,G5-Model_Assumptions!$B$3) -> -133560.7 | I5: =1/(1+Model_Assumptions!$B$8/12)^A5 -> 0.9913259 | J5: =G5*I5 -> 214561.88
A6: 2 | B6: Downside | C6: 0.35 | D6: 40808.58 | E6: 32646.87 | F6: 32200 | G6: 446.87 | H6: =IF(B6=B5,H5+G6,G6-Model_Assumptions!$B$3) -> -349553.13 | I6: =1/(1+Model_Assumptions!$B$8/12)^A6 -> 0.98272704 | J6: =G6*I6 -> 439.15123
A7: 2 | B7: Base | C7: 0.62 | D7: 131435.44 | E7: 120920.61 | F7: 28000 | G7: 92920.61 | H7: =IF(B7=B6,H6+G7,G7-Model_Assumptions!$B$3) -> -257079.39 | I7: =1/(1+Model_Assumptions!$B$8/12)^A7 -> 0.98272704 | J7: =G7*I7 -> 91315.596
A8: 2 | B8: Upside | C8: 0.82 | D8: 252059.26 | E8: 244497.48 | F8: 25760 | G8: 218737.48 | H8: =IF(B8=B7,H7+G8,G8-Model_Assumptions!$B$3) -> -131262.52 | I8: =1/(1+Model_Assumptions!$B$8/12)^A8 -> 0.98272704 | J8: =G8*I8 -> 214959.24
A9: 3 | B9: Downside | C9: 0.35 | D9: 41195.81 | E9: 32956.65 | F9: 32200 | G9: 756.65 | H9: =IF(B9=B8,H8+G9,G9-Model_Assumptions!$B$3) -> -349243.35 | I9: =1/(1+Model_Assumptions!$B$8/12)^A9 -> 0.97420276 | J9: =G9*I9 -> 737.13052
A10: 3 | B10: Base | C10: 0.62 | D10: 132682.6 | E10: 122068 | F10: 28000 | G10: 94068 | H10: =IF(B10=B9,H9+G10,G10-Model_Assumptions!$B$3) -> -255932 | I10: =1/(1+Model_Assumptions!$B$8/12)^A10 -> 0.97420276 | J10: =G10*I10 -> 91641.305
A11: 3 | B11: Upside | C11: 0.82 | D11: 254450.99 | E11: 246817.46 | F11: 25760 | G11: 221057.46 | H11: =IF(B11=B10,H10+G11,G11-Model_Assumptions!$B$3) -> -128942.54 | I11: =1/(1+Model_Assumptions!$B$8/12)^A11 -> 0.97420276 | J11: =G11*I11 -> 215354.79
A12: 4 | B12: Downside | C12: 0.35 | D12: 41586.71 | E12: 33269.37 | F12: 32200 | G12: 1069.37 | H12: =IF(B12=B11,H11+G12,G12-Model_Assumptions!$B$3) -> -348930.63 | I12: =1/(1+Model_Assumptions!$B$8/12)^A12 -> 0.96575243 | J12: =G12*I12 -> 1032.7467
A13: 4 | B13: Base | C13: 0.62 | D13: 133941.6 | E13: 123226.27 | F13: 28000 | G13: 95226.27 | H13: =IF(B13=B12,H12+G13,G13-Model_Assumptions!$B$3) -> -254773.73 | I13: =1/(1+Model_Assumptions!$B$8/12)^A13 -> 0.96575243 | J13: =G13*I13 -> 91965.002
A14: 4 | B14: Upside | C14: 0.82 | D14: 256865.43 | E14: 249159.46 | F14: 25760 | G14: 223399.46 | H14: =IF(B14=B13,H13+G14,G14-Model_Assumptions!$B$3) -> -126600.54 | I14: =1/(1+Model_Assumptions!$B$8/12)^A14 -> 0.96575243 | J14: =G14*I14 -> 215748.57
A15: 5 | B15: Downside | C15: 0.35 | D15: 41981.31 | E15: 33585.05 | F15: 32200 | G15: 1385.05 | H15: =IF(B15=B14,H14+G15,G15-Model_Assumptions!$B$3) -> -348614.95 | I15: =1/(1+Model_Assumptions!$B$8/12)^A15 -> 0.95737539 | J15: =G15*I15 -> 1326.0128
... A110: 36 | B110: Upside | C110: 0.82 | D110: 347499.13 | E110: 337074.15 | F110: 25760 | G110: 311314.15 | H110: =IF(B110=B109,H109+G110,G110-Model_Assumptions!$B$3) -> -38685.85 | I110: =1/(1+Model_Assumptions!$B$8/12)^A110 -> 0.73078947 | J110: =G110*I110 -> 227505.1

Sheet Monte_Carlo_Inputs
A2: Variable | B2: Distribution | C2: Low / Mean | D2: Most Likely / StDev | E2: High | F2: Why It Matters
A3: Adoption Rate | B3: Triangular | C3: 0.3 | D3: 0.62 | E3: 0.86 | F3: Adoption is the largest driver because a tool creates no value until people use it in workflows.
A4: Benefit Multiplier | B4: Normal | C4: 1 | D4: 0.18 | F4: Benefit uncertainty captures variance in time savings, error reduction, and faster insight generation.
A5: Monthly Cost | B5: Normal | C5: 28000 | D5: 4500 | F5: Cost uncertainty captures coaching, governance, stewardship, and maintenance needs.
A6: Risk Adjustment | B6: Triangular | C6: 0.76 | D6: 0.92 | E6: 0.98 | F6: Risk adjustment reflects data quality, review discipline, model governance, and control effectiveness.
A7: Annual Growth Rate | B7: Normal | C7: 0.1 | D7: 0.04 | F7: Growth reflects learning curve and reuse of models across teams.
A8: Discount Rate | B8: Fixed | C8: 0.105 | D8: 0 | F8: Discount rate converts future benefits into today’s dollars.
A9: Initial Investment | B9: Fixed | C9: 350000 | D9: 0 | F9: Initial investment is the starting cost of enablement and implementation.

Sheet Monte_Carlo_Trials
A2: Trial | B2: Adoption Rate | C2: Benefit Multiplier | D2: Monthly Cost | E2: Risk Adjustment | F2: Annual Growth Rate | G2: 36-Month NPV | H2: 36-Month Cumulative Benefit | I2: Break-Even Outcome
A3: 1 | B3: 0.5606 | C3: 1.0151 | D3: 25367.92 | E3: 0.9532 | F3: 0.1438 | G3: 3117052.6 | H3: 3759292.7 | I3: Break Even
A4: 2 | B4: 0.3883 | C4: 0.9772 | D4: 31659.57 | E4: 0.9233 | F4: 0.1433 | G4: 1417449.8 | H4: 1751866.9 | I4: Break Even
A5: 3 | B5: 0.4734 | C5: 0.9853 | D5: 29426.68 | E5: 0.9172 | F5: 0.1222 | G5: 2001452.3 | H5: 2435945.7 | I5: Break Even
A6: 4 | B6: 0.6794 | C6: 0.7966 | D6: 29636.72 | E6: 0.8925 | F6: 0.1272 | G6: 2439505.3 | H6: 2954732.1 | I6: Break Even
A7: 5 | B7: 0.5349 | C7: 1.3244 | D7: 32642.22 | E7: 0.8943 | F7: 0.1135 | G7: 3414584.9 | H7: 4102065.3 | I7: Break Even
A8: 6 | B8: 0.5144 | C8: 1.0525 | D8: 24025.72 | E8: 0.8841 | F8: 0.0725 | G8: 2323393.4 | H8: 2800060.8 | I8: Break Even
A9: 7 | B9: 0.6692 | C9: 0.9003 | D9: 33353.77 | E9: 0.8572 | F9: 0.0865 | G9: 2375017.3 | H9: 2867116.1 | I9: Break Even
A10: 8 | B10: 0.6794 | C10: 1.3797 | D10: 25244.66 | E10: 0.9043 | F10: 0.1277 | G10: 5374179.8 | H10: 6419707 | I10: Break Even
A11: 9 | B11: 0.4189 | C11: 0.9875 | D11: 19708.01 | E11: 0.8756 | F11: 0.1423 | G11: 1874663.1 | H11: 2287721.4 | I11: Break Even
A12: 10 | B12: 0.3963 | C12: 0.7751 | D12: 29764.41 | E12: 0.9337 | F12: 0.1296 | G12: 938866.09 | H12: 1182800.2 | I12: Break Even
A13: 11 | B13: 0.4691 | C13: 1.125 | D13: 27035.56 | E13: 0.9276 | F13: 0.0554 | G13: 2229293.9 | H13: 2684892.5 | I13: Break Even
A14: 12 | B14: 0.5079 | C14: 1.0233 | D14: 25947.52 | E14: 0.9321 | F14: 0.0967 | G14: 2418341.1 | H14: 2919482 | I14: Break Even
... A2002: 2000 | B2002: 0.5175 | C2002: 1.1346 | D2002: 24209.43 | E2002: 0.844 | F2002: 0.0694 | G2002: 2423890 | H2002: 2917375.2 | I2002: Break Even

Sheet Monte_Carlo_Live_Build
A2: LIVE BUILD SHEET: Monte Carlo Simulation
A3: Purpose: Start here during the demo. Copilot should help create or explain trial formulas, calculate simulated outcomes, summarize probabilities, and build the risk visualization. The finished Monte_Carlo_Trials and Monte_Carlo_Summary sheets remain only as answer keys/reset options.
A4: Presenter note: Build the simulation from Monte_Carlo_Inputs. The point is to construct uncertainty, not merely talk to completed outputs.
A6: Trial | B6: Adoption Rate | C6: Benefit Multiplier | D6: Monthly Cost | E6: Risk Adjustment | F6: Annual Growth Rate | G6: 36-Month NPV | H6: 36-Month Cumulative Benefit | I6: Break-Even Outcome | J6: Verification Note
A7: 1
A8: 2
A9: 3
A10: 4
A11: 5
A12: 6
A13: 7
A14: 8
A15: 9
A16: 10
A17: 11
A18: 12
... A2006: 2000

Sheet Monte_Carlo_Summary
A2: Metric | B2: Value
A3: Mean NPV | B3: 2684117.5
A4: Median NPV | B4: 2615246.3
A5: 10th Percentile NPV | B5: 1333977
A6: 90th Percentile NPV | B6: 4086282.1
A7: Probability of Positive NPV | B7: 1
A8: Probability of Breaking Even | B8: 1
A9: Average Adoption Rate | B9: 0.5942
A10: Average Risk Adjustment | B10: 0.8879

Sheet Copilot_Prompt_Library
A2: Demo | B2: Prompt to Use in Copilot in Excel | C2: Teaching Point
A3: Financial Model | B3: Look at the Financial_Model sheet. Explain the model structure in plain English for a bank executive. | C3: Copilot translates spreadsheet mechanics into executive language.
A4: Financial Model | B4: Create a summary comparing Downside, Base, and Upside outcomes by cumulative net benefit and present value. | C4: Copilot can help turn rows of model output into an investment story.
A5: Financial Model | B5: Add formulas that calculate cumulative net benefit, discount factor, and present value for each scenario. | C5: Copilot is strongest when used inside Excel because it can work with table structure and formulas.
A6: Financial Model | B6: Create a chart showing net monthly benefit by month for each scenario. | C6: Copilot can accelerate visual analysis, but the presenter should verify the chart and labels.
A7: Monte Carlo | B7: Look at the Monte_Carlo_Trials sheet. Summarize the distribution of 36-month NPV in plain English. | C7: Monte Carlo is not one forecast; it is a range of futures.
A8: Monte Carlo | B8: Create a histogram or chart that shows the risk profile of 36-month NPV. | C8: A distribution is more honest than a single-point estimate.
A9: Monte Carlo | B9: Identify which assumptions appear most associated with positive NPV and explain the pattern. | C9: Sensitivity thinking helps bankers focus on the assumptions that matter.
A10: Monte Carlo | B10: Create an executive summary: probability of positive NPV, downside risk, and what adoption rate we should protect. | C10: Risk framing turns analytics into decision support.
A11: Branch Analytics | B11: Analyze the Branch_Monthly_Data table. Which branches show strongest contribution profit and why? | C11: Bankers need performance insight, not just spreadsheet answers.
A12: Branch Analytics | B12: Find outliers in branch monthly contribution profit and explain what a manager should investigate. | C12: Outlier detection is a practical control and coaching workflow.

Sheet Branch_Summary
A2: Branch | B2: Average Deposits | C2: Average Loans | D2: Monthly Contribution Profit | E2: Digital Adoption Rate
A3: Miami Lakes | B3: 3.5335837e+08 | C3: 4.34874e+08 | D3: 492805.61 | E3: 0.62383333
A4: West Palm Beach | B4: 3.3986579e+08 | C4: 4.2936561e+08 | D4: 492627.38 | E4: 0.62685833
A5: Naples | B5: 3.2421118e+08 | C5: 3.3662358e+08 | D5: 52241.872 | E5: 0.64904167
A6: Doral | B6: 4.9134983e+08 | C6: 3.378868e+08 | D6: -219225.26 | E6: 0.49794167
A7: Coral Gables | B7: 2.1846589e+08 | C7: 2.0512714e+08 | D7: -332344.67 | E7: 0.59443333
A8: Fort Lauderdale | B8: 4.0440073e+08 | C8: 2.0352771e+08 | D8: -543921.9 | E8: 0.71484167
A9: Tampa | B9: 3.1048858e+08 | C9: 1.401756e+08 | D9: -761070.69 | E9: 0.754625
A10: Orlando | B10: 5.0802586e+08 | C10: 2.2504121e+08 | D10: -828619.12 | E10: 0.64785

Sheet Agent_Workflow_Blueprint
A2: REPEATABLE AGENT BLUEPRINT: From One Spreadsheet Demo to Shared Team Workflow
A3: Purpose: Use this sheet to design a repeatable human-supervised agent pattern that can rerun the analysis, document the steps, and share the workflow with colleagues.
A5: Agent Component | B5: What to Document | C5: Example for This Master Class
A6: Trigger | B6: When should the workflow run or be reused? | C6: Monthly analytics enablement investment review or branch performance review.
A7: Inputs | B7: Which workbook, sheets, tables, and assumptions are required? | C7: Model_Assumptions, Scenario_Assumptions, Financial_Model_Live_Build, Monte_Carlo_Inputs, Monte_Carlo_Live_Build.
A8: Prompt Pattern | B8: What role, task, output, and verification language should be reused? | C8: Act as a banking finance/risk analyst. Build the model or simulation, explain formulas, summarize decision metrics, and list verification checks.
A9: Build Steps | B9: Which formulas, charts, summaries, and memo outputs must be created each time? | C9: Scenario model, risk-adjusted benefits, NPV, simulation trials, probability of positive NPV, downside-tail chart, executive memo.
A10: Verification Controls | B10: What must a human review before sharing? | C10: Formula references, assumptions, outliers, confidential data exposure, logic of recommendation, governance fit.
A11: Output Package | B11: What should the workflow produce for others? | C11: Updated workbook, executive summary, risk chart, assumption challenge table, saved prompt log.
A12: Owner and Review | B12: Who owns the workflow and who approves changes? | C12: Workflow owner, finance/risk reviewer, business line sponsor, compliance/governance contact as needed.
A13: Versioning | B13: How will changes be tracked? | C13: Save workbook version, prompt version, data refresh date, and verification notes.
